genes2genes/AlignmentDistMan.py
genes2genes/ClusterUtils.py
genes2genes/Main.py
genes2genes/MyFunctions.py
genes2genes/OrgAlign.py
genes2genes/PathwayAnalyser.py
genes2genes/TimeSeriesPreprocessor.py
genes2genes/Utils.py
genes2genes/VisualUtils.py
genes2genes/__init__.py
genes2genes/.ipynb_checkpoints/PathwayAnalyser-checkpoint.py
genes2genes/.ipynb_checkpoints/TimeSeriesPreprocessor-checkpoint.py
genes2genes/.ipynb_checkpoints/VisualUtils-checkpoint.py
genes2genes/.ipynb_checkpoints/__init__-checkpoint.py
genes2genes-0.2.0.dist-info/LICENSE
genes2genes-0.2.0.dist-info/WHEEL
genes2genes-0.2.0.dist-info/METADATA
genes2genes-0.2.0.dist-info/RECORD
