Metadata-Version: 2.1
Name: genes2genes
Version: 0.2.0
Summary: A tool for aligning gene expression trajectories of single-cell reference and query systems
Keywords: single cell,trajectory alignment,dynamic programming
Author-email: Dinithi Sumanaweera <ds40@sanger.ac.uk>
Requires-Python: >=3.8
Classifier: License :: OSI Approved :: MIT License
Classifier: Intended Audience :: Science/Research
Classifier: Topic :: Scientific/Engineering :: Bio-Informatics
Classifier: Development Status :: 5 - Production/Stable
Requires-Dist: anndata
Requires-Dist: regex
Requires-Dist: tabulate
Requires-Dist: gseapy
Requires-Dist: blitzgsea
Requires-Dist: torch
Requires-Dist: scipy
Requires-Dist: scikit-learn
Requires-Dist: tqdm
Requires-Dist: matplotlib
Requires-Dist: numpy<2
Requires-Dist: pandas>=2.0.3
Requires-Dist: seaborn>=0.12.2
Requires-Dist: leven
Project-URL: Home, https://teichlab.github.io/Genes2Genes
Project-URL: Repository, https://github.com/Teichlab/Genes2Genes
